clg/splitup.py
clg_splitup-1.1.0.1.dist-info/LICENSE
clg_splitup-1.1.0.1.dist-info/METADATA
clg_splitup-1.1.0.1.dist-info/WHEEL
clg_splitup-1.1.0.1.dist-info/top_level.txt
clg_splitup-1.1.0.1.dist-info/RECORD
