Metadata-Version: 2.1
Name: clg-splitup
Version: 1.1.0.1
Summary: Split and organize clg CLI programs.
Home-page: http://github.com/fmenabe/python-clg-splitup
Download-URL: http://github.com/fmenabe/python-clg-splitup
Author: François Ménabé
Author-email: francois.menabe@gmail.com
License: MIT License
Keywords: command-line,argparse,wrapper,clg,framework
Classifier: Development Status :: 3 - Alpha
Classifier: Environment :: Console
Classifier: Intended Audience :: Developers
Classifier: Intended Audience :: System Administrators
Classifier: License :: OSI Approved :: MIT License
Classifier: Programming Language :: Python
Classifier: Programming Language :: Python :: 3
Classifier: Topic :: Utilities
License-File: LICENSE
Requires-Dist: clg
Requires-Dist: pyyaml
Requires-Dist: yamlloader
Requires-Dist: argcomplete
